finease/__init__.py
finease/custom_exceptions.py
finease/finease_func.py
finease/logger.py
finease-0.0.1.dist-info/LICENSE
finease-0.0.1.dist-info/METADATA
finease-0.0.1.dist-info/WHEEL
finease-0.0.1.dist-info/top_level.txt
finease-0.0.1.dist-info/RECORD
