Metadata-Version: 2.1
Name: finease
Version: 0.0.1
Summary: FinEase is a Python package for financial calculations and analysis.
Home-page: https://github.com/dipdaiict/finease
Author: dipdaiict
Author-email: dippatel256@gmail.com
License: MIT
Project-URL: Bug Tracker, https://github.com/dipdaiict/finease/issues
Classifier: Programming Language :: Python :: 3.10
Classifier: Programming Language :: Python :: 3.11
Classifier: Programming Language :: Python :: 3.12
Classifier: Operating System :: OS Independent
License-File: LICENSE
Requires-Dist: requests
Requires-Dist: ensure
Provides-Extra: testing
Requires-Dist: pytest ; extra == 'testing'
Requires-Dist: mypy ; extra == 'testing'
Requires-Dist: flake8 ; extra == 'testing'
Requires-Dist: tox ; extra == 'testing'
Requires-Dist: black ; extra == 'testing'
Requires-Dist: ensure ; extra == 'testing'
